linpxdens/__init__.py
linpxdens/core/__init__.py
linpxdens/core/line_collection.py
linpxdens/core/line_spacing_analyzer.py
linpxdens/core/line_structure_analyzer.py
linpxdens/core/utils.py
linpxdens/gui/__init__.py
linpxdens-0.0.1.dist-info/LICENSE
linpxdens-0.0.1.dist-info/METADATA
linpxdens-0.0.1.dist-info/WHEEL
linpxdens-0.0.1.dist-info/RECORD
