Metadata-Version: 2.3
Name: linpxdens
Version: 0.0.1
Summary: linpxdens (Linear pixel density) is a Python package for analyzing geometric line structures and spacing patterns in images. It provides tools for line fitting, center estimation, outlier filtering, and periodic pattern analysis based on image data. From the periodic structure, the linear pixel density is calculated.
License: MIT
Author: Clemens Trunner
Requires-Python: >=3.12.9,<4.0.0
Classifier: License :: OSI Approved :: MIT License
Classifier: Programming Language :: Python :: 3
Classifier: Programming Language :: Python :: 3.13
Requires-Dist: matplotlib (>=3.10.5,<4.0.0)
Requires-Dist: numpy (>=2.2.6,<3.0.0)
Requires-Dist: opencv-python (>=4.12.0.88,<5.0.0.0)
